opera/api/__init__.py
opera/api/cli.py
opera/api/log.py
opera/api/controllers/__init__.py
opera/api/controllers/background_invocation.py
opera/api/controllers/default.py
opera/api/openapi/__init__.py
opera/api/openapi/encoder.py
opera/api/openapi/typing_utils.py
opera/api/openapi/util.py
opera/api/openapi/models/__init__.py
opera/api/openapi/models/base_model_.py
opera/api/openapi/models/deployment_input.py
opera/api/openapi/models/diff.py
opera/api/openapi/models/diff_request.py
opera/api/openapi/models/info.py
opera/api/openapi/models/invocation.py
opera/api/openapi/models/invocation_state.py
opera/api/openapi/models/operation_success.py
opera/api/openapi/models/operation_type.py
opera/api/openapi/models/packaging_format.py
opera/api/openapi/models/packaging_input.py
opera/api/openapi/models/packaging_result.py
opera/api/openapi/models/unpackaging_input.py
opera/api/openapi/models/update_request.py
opera/api/openapi/models/validation_input.py
opera/api/openapi/models/validation_result.py
opera/api/openapi/openapi/openapi.yaml
opera_api-0.5.6.dist-info/LICENSE
opera_api-0.5.6.dist-info/METADATA
opera_api-0.5.6.dist-info/WHEEL
opera_api-0.5.6.dist-info/entry_points.txt
opera_api-0.5.6.dist-info/top_level.txt
opera_api-0.5.6.dist-info/zip-safe
opera_api-0.5.6.dist-info/RECORD
