Metadata-Version: 2.1
Name: opera-api
Version: 0.5.6
Summary: Lightweight API for xOpera orchestrator - single user, single project, single deployment
Home-page: https://github.com/xlab-si/xopera-api
Author: XLAB d.o.o.
Author-email: pypi@xlab.si
Project-URL: Documentation, https://xlab-si.github.io/xopera-docs/
Project-URL: Source Code, https://github.com/xlab-si/xopera-api
Project-URL: Bug Tracker, https://github.com/xlab-si/xopera-api/issues
Project-URL: Discussions, https://github.com/xlab-si/xopera-api/discussions
Project-URL: Releases, https://github.com/xlab-si/xopera-api/releases
Project-URL: Pre-releases, https://test.pypi.org/project/opera-api/#history
Project-URL: Examples, https://github.com/xlab-si/xopera-examples
Project-URL: CI, https://github.com/xlab-si/xopera-api/actions/
Keywords: orchestration
Classifier: Development Status :: 3 - Alpha
Classifier: Environment :: Console
Classifier: Environment :: Web Environment
Classifier: Intended Audience :: Developers
Classifier: Intended Audience :: System Administrators
Classifier: License :: OSI Approved :: Apache Software License
Classifier: Operating System :: POSIX
Classifier: Programming Language :: Python
Classifier: Programming Language :: Python :: 3
Classifier: Programming Language :: Python :: 3.8
Classifier: Programming Language :: Python :: 3.9
Classifier: Programming Language :: Python :: 3.10
Classifier: Programming Language :: Python :: 3.11
License-File: LICENSE
Requires-Dist: opera (==0.6.9)
Requires-Dist: connexion[swagger-ui] (==2.13.0)
Requires-Dist: python-dateutil (==2.8.2)
Requires-Dist: tornado (==6.1)
